Phase2/Part 1/lif.v
// =============================================================
// lif.v — Leaky Integrate-and-Fire 神經元模組
// =============================================================
//
// 這個模組實作 Day 4 的四行公式：
//   mem = (BETA * mem) >> FRAC_BITS   // 衰減
//   mem = mem + cur                    // 累加
//   spk = (mem >= THRESHOLD)           // 判斷
//   if (spk) mem = mem - THRESHOLD     // reset
//
// 介面：
//   clk, rst_n    — 時脈和非同步低態重置
//   en            — 致能（高態時更新膜電位）
//   cur_in        — 突觸電流（來自 MAC 單元）
//   spk_out       — spike 輸出（1-bit）
//   mem_out        — 膜電位輸出（用於 debug / testbench 觀察）
//
// 參數：
//   MEM_WIDTH     — 膜電位位寬（預設 16）
//   CUR_WIDTH     — 輸入電流位寬（預設 16）
//   FRAC_BITS     — 定點數小數位數（預設 5）
//   BETA          — 衰減係數的定點表示（預設 30 = 0.95 × 32）
//   THRESHOLD     — 閾值的定點表示（預設 32 = 1.0 × 32）
//
// =============================================================

module lif #(
    parameter MEM_WIDTH  = 16,       // 膜電位位寬（比權重寬，避免溢位）
    parameter CUR_WIDTH  = 16,       // 輸入電流位寬
    parameter FRAC_BITS  = 5,        // 小數位數
    parameter BETA       = 30,       // 0.95 × 2^5 = 30.4 ≈ 30
    parameter THRESHOLD  = 32        // 1.0 × 2^5 = 32
)(
    input  wire                     clk,
    input  wire                     rst_n,    // active-low reset
    input  wire                     en,       // 致能信號
    input  wire signed [CUR_WIDTH-1:0] cur_in,   // 突觸電流
    output wire                     spk_out,  // spike 輸出
    output wire signed [MEM_WIDTH-1:0] mem_out   // 膜電位（debug 用）
);

    // ─── 內部信號 ───
    reg  signed [MEM_WIDTH-1:0] mem;        // 膜電位暫存器

    // 中間運算需要更寬的位數，避免乘法溢位
    // BETA (≤32, 6-bit) × mem (16-bit) = 最多 22-bit
    wire signed [MEM_WIDTH+6-1:0] decay_product;
    wire signed [MEM_WIDTH-1:0]   decayed_mem;
    wire signed [MEM_WIDTH-1:0]   new_mem;
    wire                          spike;

    // ─── Step 1: 膜電位衰減 ───
    // Python: mem = (beta * mem) >> FRAC_BITS
    //
    // 定點數乘法：BETA 是 Q2.5，mem 是 Q?.5
    // 乘積是 Q?.10，右移 5 位變回 Q?.5
    // 用算術右移（>>>）保留符號位
    assign decay_product = BETA * mem;
    assign decayed_mem   = decay_product >>> FRAC_BITS;

    // ─── Step 2: 累加輸入電流 ───
    // Python: mem = mem + cur
    assign new_mem = decayed_mem + cur_in;

    // ─── Step 3: Spike 判斷 ───
    // Python: spk = (mem >= threshold)
    assign spike = (new_mem >= THRESHOLD);

    // ─── 輸出 ───
    assign spk_out = spike;
    assign mem_out = mem;

    // ─── 時序邏輯：更新膜電位 ───
    always @(posedge clk or negedge rst_n) begin
        if (!rst_n) begin
            // Reset：膜電位歸零
            mem <= 0;
        end
        else if (en) begin
            // Step 4: Reset by subtraction
            // Python: if (spk) mem = mem - threshold
            if (spike)
                mem <= new_mem - THRESHOLD;
            else
                mem <= new_mem;
        end
        // else: en=0 時，膜電位保持不變
    end

endmodule

Phase2/Part1/tb_lif.v
// =============================================================
// tb_lif.v — LIF 神經元 Testbench
// =============================================================
//
// 測試策略：
//   1. 注入固定電流，觀察膜電位累積和 spike 行為
//   2. 跟 Day 4 的 Python 參考模型比對
//   3. 測試邊界情況（reset, 零輸入, 負電流）
//
// 在 Vivado 中跑：
//   直接加入 Simulation Source，跑 behavioral simulation
//
// 或用 iverilog（免費）：
//   iverilog -o tb_lif tb_lif.v lif.v
//   vvp tb_lif
//
// =============================================================

`timescale 1ns / 1ps

module tb_lif;

    // ─── 參數 ───
    parameter MEM_WIDTH  = 16;
    parameter CUR_WIDTH  = 16;
    parameter FRAC_BITS  = 5;
    parameter BETA       = 30;     // 0.95 × 32
    parameter THRESHOLD  = 32;     // 1.0 × 32
    parameter NUM_STEPS  = 25;

    // ─── 信號宣告 ───
    reg                         clk;
    reg                         rst_n;
    reg                         en;
    reg  signed [CUR_WIDTH-1:0] cur_in;
    wire                        spk_out;
    wire signed [MEM_WIDTH-1:0] mem_out;

    // ─── 實例化 LIF 模組 ───
    lif #(
        .MEM_WIDTH(MEM_WIDTH),
        .CUR_WIDTH(CUR_WIDTH),
        .FRAC_BITS(FRAC_BITS),
        .BETA(BETA),
        .THRESHOLD(THRESHOLD)
    ) uut (
        .clk(clk),
        .rst_n(rst_n),
        .en(en),
        .cur_in(cur_in),
        .spk_out(spk_out),
        .mem_out(mem_out)
    );

    // ─── Clock 產生（10ns 週期 = 100MHz）───
    initial clk = 0;
    always #5 clk = ~clk;

    // ─── 測試記錄 ───
    integer spike_count;
    integer test_pass;
    integer test_fail;
    integer t;

    // ─── Python 參考值 ───
    // Day 4 的結果：input=0.3 (=9.6→10 in fixed point), beta=0.95
    // Python spike times: [3, 7, 11, 15, 18, 22]
    //
    // 注意：Python 用 input=0.3×32=9.6→round→10
    // 但 Day 4 的 fixed_inference 是對整張圖片做矩陣乘法後的結果
    // 這裡我們用簡化的固定電流來測試 LIF 本身的邏輯

    // ─── VCD 波形輸出（給 GTKWave 用）───
    initial begin
        $dumpfile("tb_lif.vcd");
        $dumpvars(0, tb_lif);
    end

    // ─── 主測試程序 ───
    initial begin
        $display("==================================================");
        $display("  LIF Neuron Testbench");
        $display("==================================================");
        $display("  BETA=%0d, THRESHOLD=%0d, FRAC_BITS=%0d",
                 BETA, THRESHOLD, FRAC_BITS);
        $display("");

        test_pass = 0;
        test_fail = 0;

        // ─── Test 1：Reset 行為 ───
        $display("--- Test 1: Reset ---");
        rst_n = 0;
        en    = 0;
        cur_in = 0;
        @(posedge clk);
        @(posedge clk);
        rst_n = 1;
        @(posedge clk);

        if (mem_out == 0) begin
            $display("  PASS: mem = 0 after reset");
            test_pass = test_pass + 1;
        end else begin
            $display("  FAIL: mem = %0d after reset (expected 0)", mem_out);
            test_fail = test_fail + 1;
        end

        // ─── Test 2：固定電流注入，觀察 spike ───
        $display("");
        $display("--- Test 2: Fixed current injection ---");
        $display("  Injecting cur_in = 10 (= 0.3125 in Q2.5)");
        $display("  Expected: membrane accumulates, spikes periodically");
        $display("");

        // Reset
        rst_n = 0;
        @(posedge clk);
        rst_n = 1;
        en = 1;
        cur_in = 10;  // 10/32 = 0.3125，接近 Day 4 的 0.3

        spike_count = 0;

        $display("  step | mem_before | cur_in | mem_after | spike");
        $display("  -----+------------+--------+-----------+------");

        for (t = 0; t < NUM_STEPS; t = t + 1) begin
            @(posedge clk);
            #1;  // 等一下讓信號穩定

            if (spk_out) spike_count = spike_count + 1;

            $display("  %4d | %10d | %6d | %9d | %s",
                     t, mem_out, cur_in,
                     (spk_out) ? mem_out : mem_out,
                     (spk_out) ? "SPIKE!" : "      ");
        end

        $display("");
        $display("  Total spikes: %0d (in %0d steps)", spike_count, NUM_STEPS);

        // Day 4 Python 參考：0.3 的電流大約每 3-4 步 spike 一次
        // 0.3125 略大於 0.3，所以 spike 頻率應該略高
        if (spike_count >= 5 && spike_count <= 8) begin
            $display("  PASS: spike count in expected range [5, 8]");
            test_pass = test_pass + 1;
        end else begin
            $display("  FAIL: spike count %0d outside expected range", spike_count);
            test_fail = test_fail + 1;
        end

        // ─── Test 3：零輸入，膜電位應該逐漸衰減 ───
        $display("");
        $display("--- Test 3: Zero input (leak only) ---");

        // 先注入一些電流讓膜電位升高
        rst_n = 0;
        @(posedge clk);
        rst_n = 1;
        en = 1;
        cur_in = 20;  // 較大電流
        @(posedge clk);
        @(posedge clk);
        @(posedge clk);

        // 切到零輸入
        cur_in = 0;
        $display("  Membrane should decay towards 0:");

        for (t = 0; t < 30; t = t + 1) begin
            @(posedge clk);
            #1;
            if (t < 10 || t == 14 || t == 19 || t == 24 || t == 29)
                $display("  t=%0d: mem = %0d", t, mem_out);
        end

        // beta=30/32=0.9375, 從 ~20 開始衰減
        // 30 步後：20 × 0.9375^30 ≈ 2.8，應小於 5
        if (mem_out >= 0 && mem_out <= 5) begin
            $display("  PASS: membrane decayed near 0 (mem=%0d)", mem_out);
            test_pass = test_pass + 1;
        end else begin
            $display("  FAIL: membrane = %0d (expected <= 5 after 30 steps)", mem_out);
            test_fail = test_fail + 1;
        end

        // ─── Test 4：en=0 時膜電位應保持不變 ───
        $display("");
        $display("--- Test 4: Enable control ---");

        rst_n = 0;
        @(posedge clk);
        rst_n = 1;
        en = 1;
        cur_in = 15;
        @(posedge clk);
        @(posedge clk);
        #1;

        begin : enable_test
            reg signed [MEM_WIDTH-1:0] mem_before_disable;
            mem_before_disable = mem_out;

            en = 0;  // 停止更新
            cur_in = 100;  // 即使電流很大也不應該影響
            @(posedge clk);
            @(posedge clk);
            @(posedge clk);
            #1;

            if (mem_out == mem_before_disable) begin
                $display("  PASS: membrane unchanged when en=0 (mem=%0d)", mem_out);
                test_pass = test_pass + 1;
            end else begin
                $display("  FAIL: membrane changed when en=0 (%0d -> %0d)",
                         mem_before_disable, mem_out);
                test_fail = test_fail + 1;
            end
        end

        // ─── Test 5：負電流（抑制性突觸）───
        $display("");
        $display("--- Test 5: Negative current (inhibitory) ---");

        rst_n = 0;
        @(posedge clk);
        rst_n = 1;
        en = 1;
        cur_in = -5;  // 負電流
        spike_count = 0;

        for (t = 0; t < 20; t = t + 1) begin
            @(posedge clk);
            #1;
            if (spk_out) spike_count = spike_count + 1;
        end

        if (spike_count == 0) begin
            $display("  PASS: no spikes with negative current (as expected)");
            test_pass = test_pass + 1;
        end else begin
            $display("  FAIL: %0d spikes with negative current", spike_count);
            test_fail = test_fail + 1;
        end

        // ─── 測試結果摘要 ───
        $display("");
        $display("==================================================");
        $display("  Results: %0d PASS, %0d FAIL", test_pass, test_fail);
        $display("==================================================");

        if (test_fail == 0)
            $display("  All tests passed!");
        else
            $display("  WARNING: %0d test(s) failed!", test_fail);

        $display("");
        $finish;
    end

endmodule

Phase2/Part1/tb_lif.vcd
$date
	Fri Mar 20 10:02:37 2026
$end
$version
	Icarus Verilog
$end
$timescale
	1ps
$end
$scope module tb_lif $end
$var wire 1 ! spk_out $end
$var wire 16 " mem_out [15:0] $end
$var parameter 32 # BETA $end
$var parameter 32 $ CUR_WIDTH $end
$var parameter 32 % FRAC_BITS $end
$var parameter 32 & MEM_WIDTH $end
$var parameter 32 ' NUM_STEPS $end
$var parameter 32 ( THRESHOLD $end
$var reg 1 ) clk $end
$var reg 16 * cur_in [15:0] $end
$var reg 1 + en $end
$var reg 1 , rst_n $end
$var integer 32 - spike_count [31:0] $end
$var integer 32 . t [31:0] $end
$var integer 32 / test_fail [31:0] $end
$var integer 32 0 test_pass [31:0] $end
$scope module uut $end
$var wire 1 ) clk $end
$var wire 16 1 cur_in [15:0] $end
$var wire 1 + en $end
$var wire 16 2 mem_out [15:0] $end
$var wire 1 , rst_n $end
$var wire 1 ! spk_out $end
$var wire 1 3 spike $end
$var wire 16 4 new_mem [15:0] $end
$var wire 16 5 decayed_mem [15:0] $end
$var wire 22 6 decay_product [21:0] $end
$var parameter 32 7 BETA $end
$var parameter 32 8 CUR_WIDTH $end
$var parameter 32 9 FRAC_BITS $end
$var parameter 32 : MEM_WIDTH $end
$var parameter 32 ; THRESHOLD $end
$var reg 16 < mem [15:0] $end
$upscope $end
$scope begin enable_test $end
$var reg 16 = mem_before_disable [15:0] $end
$upscope $end
$upscope $end
$enddefinitions $end
$comment Show the parameter values. $end
$dumpall
b100000 ;
b10000 :
b101 9
b10000 8
b11110 7
b100000 (
b11001 '
b10000 &
b101 %
b10000 $
b11110 #
$end
#0
$dumpvars
bx =
b0 <
b0 6
b0 5
b0 4
03
b0 2
b0 1
b0 0
b0 /
bx .
bx -
0,
0+
b0 *
0)
b0 "
0!
$end
#5000
1)
#10000
0)
#15000
1,
1)
#20000
0)
#25000
0,
b1 0
1)
#30000
0)
#35000
b1001 5
b100101100 6
b1010 "
b1010 2
b1010 <
b0 .
b0 -
b10011 4
b1010 *
b1010 1
1+
1,
1)
#40000
0)
#45000
b11011 4
b10001 5
b1000111010 6
b10011 "
b10011 2
b10011 <
1)
#46000
b1 .
#50000
0)
#55000
1!
13
b100011 4
b11001 5
b1100101010 6
b11011 "
b11011 2
b11011 <
1)
#56000
b10 .
b1 -
#60000
0)
#65000
0!
03
b1100 4
b10 5
b1011010 6
b11 "
b11 2
b11 <
1)
#66000
b11 .
#70000
0)
#75000
b10101 4
b1011 5
b101101000 6
b1100 "
b1100 2
b1100 <
1)
#76000
b100 .
#80000
0)
#85000
b11101 4
b10011 5
b1001110110 6
b10101 "
b10101 2
b10101 <
1)
#86000
b101 .
#90000
0)
#95000
1!
13
b100101 4
b11011 5
b1101100110 6
b11101 "
b11101 2
b11101 <
1)
#96000
b110 .
b10 -
#100000
0)
#105000
0!
03
b1110 4
b100 5
b10010110 6
b101 "
b101 2
b101 <
1)
#106000
b111 .
#110000
0)
#115000
b10111 4
b1101 5
b110100100 6
b1110 "
b1110 2
b1110 <
1)
#116000
b1000 .
#120000
0)
#125000
b11111 4
b10101 5
b1010110010 6
b10111 "
b10111 2
b10111 <
1)
#126000
b1001 .
#130000
0)
#135000
1!
13
b100111 4
b11101 5
b1110100010 6
b11111 "
b11111 2
b11111 <
1)
#136000
b1010 .
b11 -
#140000
0)
#145000
0!
03
b10000 4
b110 5
b11010010 6
b111 "
b111 2
b111 <
1)
#146000
b1011 .
#150000
0)
#155000
b11001 4
b1111 5
b111100000 6
b10000 "
b10000 2
b10000 <
1)
#156000
b1100 .
#160000
0)
#165000
1!
13
b100001 4
b10111 5
b1011101110 6
b11001 "
b11001 2
b11001 <
1)
#166000
b1101 .
b100 -
#170000
0)
#175000
0!
03
b1010 4
b0 5
b11110 6
b1 "
b1 2
b1 <
1)
#176000
b1110 .
#180000
0)
#185000
b10011 4
b1001 5
b100101100 6
b1010 "
b1010 2
b1010 <
1)
#186000
b1111 .
#190000
0)
#195000
b11011 4
b10001 5
b1000111010 6
b10011 "
b10011 2
b10011 <
1)
#196000
b10000 .
#200000
0)
#205000
1!
13
b100011 4
b11001 5
b1100101010 6
b11011 "
b11011 2
b11011 <
1)
#206000
b10001 .
b101 -
#210000
0)
#215000
0!
03
b1100 4
b10 5
b1011010 6
b11 "
b11 2
b11 <
1)
#216000
b10010 .
#220000
0)
#225000
b10101 4
b1011 5
b101101000 6
b1100 "
b1100 2
b1100 <
1)
#226000
b10011 .
#230000
0)
#235000
b11101 4
b10011 5
b1001110110 6
b10101 "
b10101 2
b10101 <
1)
#236000
b10100 .
#240000
0)
#245000
1!
13
b100101 4
b11011 5
b1101100110 6
b11101 "
b11101 2
b11101 <
1)
#246000
b10101 .
b110 -
#250000
0)
#255000
0!
03
b1110 4
b100 5
b10010110 6
b101 "
b101 2
b101 <
1)
#256000
b10110 .
#260000
0)
#265000
b10111 4
b1101 5
b110100100 6
b1110 "
b1110 2
b1110 <
1)
#266000
b10111 .
#270000
0)
#275000
b11111 4
b10101 5
b1010110010 6
b10111 "
b10111 2
b10111 <
1)
#276000
b11000 .
#280000
0)
#285000
1!
13
b100111 4
b11101 5
b1110100010 6
b11111 "
b11111 2
b11111 <
1)
#286000
0!
03
b1010 4
b0 5
b0 6
b0 "
b0 2
b0 <
0,
b10 0
b11001 .
b111 -
#290000
0)
#295000
1!
13
b10010 5
b1001011000 6
b10100 "
b10100 2
b10100 <
b100110 4
b10100 *
b10100 1
1,
1)
#300000
0)
#305000
0!
03
b11001 4
b101 5
b10110100 6
b110 "
b110 2
b110 <
1)
#310000
0)
#315000
1!
13
b101011 4
b10111 5
b1011101110 6
b11001 "
b11001 2
b11001 <
1)
#320000
0)
#325000
b10101 5
b1010110010 6
b10111 "
b10111 2
b10111 <
b0 .
0!
03
b10101 4
b0 *
b0 1
1)
#330000
0)
#335000
b10011 4
b10011 5
b1001110110 6
b10101 "
b10101 2
b10101 <
1)
#336000
b1 .
#340000
0)
#345000
b10001 4
b10001 5
b1000111010 6
b10011 "
b10011 2
b10011 <
1)
#346000
b10 .
#350000
0)
#355000
b1111 4
b1111 5
b111111110 6
b10001 "
b10001 2
b10001 <
1)
#356000
b11 .
#360000
0)
#365000
b1110 4
b1110 5
b111000010 6
b1111 "
b1111 2
b1111 <
1)
#366000
b100 .
#370000
0)
#375000
b1101 4
b1101 5
b110100100 6
b1110 "
b1110 2
b1110 <
1)
#376000
b101 .
#380000
0)
#385000
b1100 4
b1100 5
b110000110 6
b1101 "
b1101 2
b1101 <
1)
#386000
b110 .
#390000
0)
#395000
b1011 4
b1011 5
b101101000 6
b1100 "
b1100 2
b1100 <
1)
#396000
b111 .
#400000
0)
#405000
b1010 4
b1010 5
b101001010 6
b1011 "
b1011 2
b1011 <
1)
#406000
b1000 .
#410000
0)
#415000
b1001 4
b1001 5
b100101100 6
b1010 "
b1010 2
b1010 <
1)
#416000
b1001 .
#420000
0)
#425000
b1000 4
b1000 5
b100001110 6
b1001 "
b1001 2
b1001 <
1)
#426000
b1010 .
#430000
0)
#435000
b111 4
b111 5
b11110000 6
b1000 "
b1000 2
b1000 <
1)
#436000
b1011 .
#440000
0)
#445000
b110 4
b110 5
b11010010 6
b111 "
b111 2
b111 <
1)
#446000
b1100 .
#450000
0)
#455000
b101 4
b101 5
b10110100 6
b110 "
b110 2
b110 <
1)
#456000
b1101 .
#460000
0)
#465000
b100 4
b100 5
b10010110 6
b101 "
b101 2
b101 <
1)
#466000
b1110 .
#470000
0)
#475000
b11 4
b11 5
b1111000 6
b100 "
b100 2
b100 <
1)
#476000
b1111 .
#480000
0)
#485000
b10 4
b10 5
b1011010 6
b11 "
b11 2
b11 <
1)
#486000
b10000 .
#490000
0)
#495000
b1 4
b1 5
b111100 6
b10 "
b10 2
b10 <
1)
#496000
b10001 .
#500000
0)
#505000
b0 4
b0 5
b11110 6
b1 "
b1 2
b1 <
1)
#506000
b10010 .
#510000
0)
#515000
b0 6
b0 "
b0 2
b0 <
1)
#516000
b10011 .
#520000
0)
#525000
1)
#526000
b10100 .
#530000
0)
#535000
1)
#536000
b10101 .
#540000
0)
#545000
1)
#546000
b10110 .
#550000
0)
#555000
1)
#556000
b10111 .
#560000
0)
#565000
1)
#566000
b11000 .
#570000
0)
#575000
1)
#576000
b11001 .
#580000
0)
#585000
1)
#586000
b11010 .
#590000
0)
#595000
1)
#596000
b11011 .
#600000
0)
#605000
1)
#606000
b11100 .
#610000
0)
#615000
1)
#616000
b11101 .
#620000
0)
#625000
1)
#626000
0,
b11 0
b11110 .
#630000
0)
#635000
b1110 5
b111000010 6
b1111 "
b1111 2
b1111 <
b11101 4
b1111 *
b1111 1
1,
1)
#640000
0)
#645000
1!
13
b101010 4
b11011 5
b1101100110 6
b11101 "
b11101 2
b11101 <
1)
#650000
0)
#655000
0!
03
b11000 4
b1001 5
b100101100 6
b1010 "
b1010 2
b1010 <
1)
#656000
1!
13
b1101101 4
b1100100 *
b1100100 1
0+
b1010 =
#660000
0)
#665000
1)
#670000
0)
#675000
1)
#680000
0)
#685000
1)
#686000
b1100100 4
b0 5
b0 6
b0 "
b0 2
b0 <
0,
b100 0
#690000
0)
#695000
b1111111111111011 5
b1111111111111101101010 6
b1111111111111011 "
b1111111111111011 2
b1111111111111011 <
b0 .
b0 -
0!
03
b1111111111110110 4
b1111111111111011 *
b1111111111111011 1
1+
1,
1)
#700000
0)
#705000
b1111111111110001 4
b1111111111110110 5
b1111111111111011010100 6
b1111111111110110 "
b1111111111110110 2
b1111111111110110 <
1)
#706000
b1 .
#710000
0)
#715000
b1111111111101100 4
b1111111111110001 5
b1111111111111000111110 6
b1111111111110001 "
b1111111111110001 2
b1111111111110001 <
1)
#716000
b10 .
#720000
0)
#725000
b1111111111101000 4
b1111111111101101 5
b1111111111110110101000 6
b1111111111101100 "
b1111111111101100 2
b1111111111101100 <
1)
#726000
b11 .
#730000
0)
#735000
b1111111111100100 4
b1111111111101001 5
b1111111111110100110000 6
b1111111111101000 "
b1111111111101000 2
b1111111111101000 <
1)
#736000
b100 .
#740000
0)
#745000
b1111111111100000 4
b1111111111100101 5
b1111111111110010111000 6
b1111111111100100 "
b1111111111100100 2
b1111111111100100 <
1)
#746000
b101 .
#750000
0)
#755000
b1111111111011101 4
b1111111111100010 5
b1111111111110001000000 6
b1111111111100000 "
b1111111111100000 2
b1111111111100000 <
1)
#756000
b110 .
#760000
0)
#765000
b1111111111011010 4
b1111111111011111 5
b1111111111101111100110 6
b1111111111011101 "
b1111111111011101 2
b1111111111011101 <
1)
#766000
b111 .
#770000
0)
#775000
b1111111111010111 4
b1111111111011100 5
b1111111111101110001100 6
b1111111111011010 "
b1111111111011010 2
b1111111111011010 <
1)
#776000
b1000 .
#780000
0)
#785000
b1111111111010100 4
b1111111111011001 5
b1111111111101100110010 6
b1111111111010111 "
b1111111111010111 2
b1111111111010111 <
1)
#786000
b1001 .
#790000
0)
#795000
b1111111111010001 4
b1111111111010110 5
b1111111111101011011000 6
b1111111111010100 "
b1111111111010100 2
b1111111111010100 <
1)
#796000
b1010 .
#800000
0)
#805000
b1111111111001110 4
b1111111111010011 5
b1111111111101001111110 6
b1111111111010001 "
b1111111111010001 2
b1111111111010001 <
1)
#806000
b1011 .
#810000
0)
#815000
b1111111111001100 4
b1111111111010001 5
b1111111111101000100100 6
b1111111111001110 "
b1111111111001110 2
b1111111111001110 <
1)
#816000
b1100 .
#820000
0)
#825000
b1111111111001010 4
b1111111111001111 5
b1111111111100111101000 6
b1111111111001100 "
b1111111111001100 2
b1111111111001100 <
1)
#826000
b1101 .
#830000
0)
#835000
b1111111111001000 4
b1111111111001101 5
b1111111111100110101100 6
b1111111111001010 "
b1111111111001010 2
b1111111111001010 <
1)
#836000
b1110 .
#840000
0)
#845000
b1111111111000110 4
b1111111111001011 5
b1111111111100101110000 6
b1111111111001000 "
b1111111111001000 2
b1111111111001000 <
1)
#846000
b1111 .
#850000
0)
#855000
b1111111111000100 4
b1111111111001001 5
b1111111111100100110100 6
b1111111111000110 "
b1111111111000110 2
b1111111111000110 <
1)
#856000
b10000 .
#860000
0)
#865000
b1111111111000010 4
b1111111111000111 5
b1111111111100011111000 6
b1111111111000100 "
b1111111111000100 2
b1111111111000100 <
1)
#866000
b10001 .
#870000
0)
#875000
b1111111111000000 4
b1111111111000101 5
b1111111111100010111100 6
b1111111111000010 "
b1111111111000010 2
b1111111111000010 <
1)
#876000
b10010 .
#880000
0)
#885000
b1111111110111111 4
b1111111111000100 5
b1111111111100010000000 6
b1111111111000000 "
b1111111111000000 2
b1111111111000000 <
1)
#886000
b10011 .
#890000
0)
#895000
b1111111110111110 4
b1111111111000011 5
b1111111111100001100010 6
b1111111110111111 "
b1111111110111111 2
b1111111110111111 <
1)
#896000
b101 0
b10100 .
